urlfix/__init__.py
urlfix/__main__.py
urlfix/dirurlfix.py
urlfix/urlfix.py
urlfix/version.py
urlfix-0.2.2.dist-info/LICENSE
urlfix-0.2.2.dist-info/METADATA
urlfix-0.2.2.dist-info/WHEEL
urlfix-0.2.2.dist-info/top_level.txt
urlfix-0.2.2.dist-info/RECORD
