Metadata-Version: 2.1
Name: urlfix
Version: 0.2.2
Summary: Check and Fix Outdated URLs
Home-page: http://www.github.com/Nelson-Gon/urlfix
Author: Nelson Gonzabato
Author-email: gonzabato@hotmail.com
License: MIT
Download-URL: https://github.com/Nelson-Gon/urlfix/archive/refs/tags/v0.2.2.zip
Keywords: development url https markdown web url-validation url-checker
Platform: UNKNOWN
Requires-Python: >=3.6
